[
        { "modelo": "Yaris", 
          "version": "XS AUDIO 5P", 
          "modalidad": "70/30", 
          "image": "/imagenes/tpa/yaris100.png",
          "slug": "yaris-xs-audio-5p-7030",
          "cuotas": [
          			{ "cuota": "Cuota 1", 
          			  "valor": "15.704,18"
          			},
          			{ "cuota": "Cuotas 2 a 5", 
          			  "valor": "21.148,50"
          			},
          			{ "cuota": "Cuotas 6 a 24", 
          			  "valor": "18.817,13"
          			},
          			{ "cuota": "Cuotas 25 a 84", 
          			  "valor": "20.606,01"
          			}
        		  		  ]
        },
        { "modelo": "Yaris", 
          "version": "XS 5P", 
          "modalidad": "100%",
          "image": "/imagenes/tpa/yaris100.png", 
          "slug": "yaris-xs-hatchback",
          "cuotas": [
                { "cuota": "Cuota 1",
                  "valor": "21.786,67"
                },
                { "cuota": "Cuotas 2 a 5",
                  "valor": "24.862,48"
                },
                { "cuota": "Cuotas 6 a 24",
                  "valor": "25.074,41"
                },
                { "cuota": "Cuotas 25 a 84",
                  "valor": "28.869,36"
                }
                    ]
        },
        { "modelo": "Hilux", 
          "version": "CD 4x2 DX", 
          "modalidad": "70/30", 
          "image": "/imagenes/tpa/hilux7030.png",
          "slug": "hilux-4x2-dx-7030",
          "cuotas": [
          			{ "cuota": "Cuota 1", 
          			  "valor": "33.543,29"
          			},
          			{ "cuota": "Cuotas 2 a 5", 
          			  "valor": "38.848,85"
          			},
          			{ "cuota": "Cuotas 6 a 24", 
          			  "valor": "34.829,29"
          			},
          			{ "cuota": "Cuotas 25 a 84", 
          			  "valor": "34.429,39"
          			}
        		  		  ]
        },
        { "modelo": "Hilux", 
          "version": "CD 4x4 DX", 
          "modalidad": "100%",
          "image": "/imagenes/tpa/hilux100.png", 
          "slug": "hilux-4x4-dx-100",
          "cuotas": [
          			{ "cuota": "Cuota 1",
          			  "valor": "48.131,10"
          			},
          			{ "cuota": "Cuotas 2 a 5",
          			  "valor": "54.321,08"
          			},
          			{ "cuota": "Cuotas 6 a 24",
          			  "valor": "54.747,77"
          			},
          			{ "cuota": "Cuotas 25 a 84",
          			  "valor": "56.414,35"
          			}
        		  		  ]
        },
        { "modelo": "Corolla", 
          "version": "XLI M/T", 
          "modalidad": "100%",
          "image": "/imagenes/tpa/corolla100.png", 
          "slug": "corolla-xli-mt-100",
          "cuotas": [
                { "cuota": "Cuota 1",
                  "valor": "28.536,78"
                },
                { "cuota": "Cuotas 2 a 5",
                  "valor": "32.206,80"
                },
                { "cuota": "Cuotas 6 a 24",
                  "valor": "32.459,79"
                },
                { "cuota": "Cuotas 25 a 84",
                  "valor": "33.447,89"
                }
                    ]
        },
        { "modelo": "Corolla Cross", 
          "version": "XEI CVT", 
          "modalidad": "100%",
          "image": "/imagenes/tpa/corolla-cross100.png", 
          "slug": "corolla-cross-xei-cvt-100",
          "cuotas": [
                { "cuota": "Cuota 1",
                  "valor": "42.977,39"
                },
                { "cuota": "Cuotas 2 a 5",
                  "valor": "48.504,56"
                },
                { "cuota": "Cuotas 6 a 24",
                  "valor": "48.885,57"
                },
                { "cuota": "Cuotas 25 a 84",
                  "valor": "50.373,69"
                }
                    ]
        }
]